mwdb/__init__.py
mwdb/errors.py
mwdb/schema.py
mwdb-0.1.2.dist-info/DESCRIPTION.rst
mwdb-0.1.2.dist-info/METADATA
mwdb-0.1.2.dist-info/RECORD
mwdb-0.1.2.dist-info/WHEEL
mwdb-0.1.2.dist-info/metadata.json
mwdb-0.1.2.dist-info/top_level.txt
