Metadata-Version: 2.0
Name: mwdb
Version: 0.1.2
Summary: A set of utilities for connecting to and querying a MediaWiki database.
Home-page: http://pypi.python.org/pypi/mwdb
Author: Aaron Halfaker
Author-email: aaron.halfaker@gmail.com
License: The MIT License (MIT)
Requires-Dist: pymysql
Requires-Dist: sqlalchemy
